{
  "gitSyncId": "65259f9c2be41c5c758b0400_65355b479700161317ae5b62",
  "id": "Page1_get_research_focus",
  "pluginId": "postgres-plugin",
  "pluginType": "DB",
  "unpublishedAction": {
    "actionConfiguration": {
      "body": "SELECT * FROM public.\"focus\";",
      "encodeParamsToggle": true,
      "paginationType": "NONE",
      "pluginSpecifiedTemplates": [
        {
          "value": true
        }
      ],
      "timeoutInMillisecond": 10000
    },
    "confirmBeforeExecute": false,
    "datasource": {
      "id": "urc",
      "isAutoGenerated": false,
      "name": "urc",
      "pluginId": "postgres-plugin"
    },
    "dynamicBindingPathList": [],
    "executeOnLoad": false,
    "name": "get_research_focus",
    "pageId": "Page1",
    "userSetOnLoad": false
  }
}